popoll_backend/__main__.py
popoll_backend/db/__init__.py
popoll_backend/db/model/__init__.py
popoll_backend/db/model/answer.py
popoll_backend/db/model/date.py
popoll_backend/db/model/instrument.py
popoll_backend/db/model/option.py
popoll_backend/db/model/session.py
popoll_backend/db/model/user.py
popoll_backend/db/model/user_instruments.py
popoll_backend/db/query/__init__.py
popoll_backend/db/query/answer_queries.py
popoll_backend/db/query/date_queries.py
popoll_backend/db/query/instrument_queries.py
popoll_backend/db/query/option_queries.py
popoll_backend/db/query/session_queries.py
popoll_backend/db/query/user_instruments_queries.py
popoll_backend/db/query/user_queries.py
popoll_backend/model/__init__.py
popoll_backend/model/output/__init__.py
popoll_backend/model/output/history.py
popoll_backend/usecases/__init__.py
popoll_backend/usecases/all/__init__.py
popoll_backend/usecases/all/delete_old_dates.py
popoll_backend/usecases/all/get_all_sessions.py
popoll_backend/usecases/all/upload_polls.py
popoll_backend/usecases/poll/__init__.py
popoll_backend/usecases/poll/answer/__init__.py
popoll_backend/usecases/poll/answer/create_answer.py
popoll_backend/usecases/poll/answer/delete_answer.py
popoll_backend/usecases/poll/answer/get_answer.py
popoll_backend/usecases/poll/answer/get_answer_search.py
popoll_backend/usecases/poll/answer/update_answer.py
popoll_backend/usecases/poll/date/__init__.py
popoll_backend/usecases/poll/date/create_date.py
popoll_backend/usecases/poll/date/date_details.py
popoll_backend/usecases/poll/date/delete_date.py
popoll_backend/usecases/poll/date/get_date.py
popoll_backend/usecases/poll/date/get_date_details.py
popoll_backend/usecases/poll/date/get_dates.py
popoll_backend/usecases/poll/date/get_dates_user.py
popoll_backend/usecases/poll/date/update_date.py
popoll_backend/usecases/poll/instrument/__init__.py
popoll_backend/usecases/poll/instrument/get_instrument.py
popoll_backend/usecases/poll/instrument/get_instruments.py
popoll_backend-0.0.73.dist-info/licenses/LICENSE
popoll_backend-0.0.73.dist-info/METADATA
popoll_backend-0.0.73.dist-info/WHEEL
popoll_backend-0.0.73.dist-info/top_level.txt
popoll_backend-0.0.73.dist-info/RECORD
