Metadata-Version: 2.4
Name: popoll_backend
Version: 0.0.73
Summary: A small example package
Author-email: vivi5421 <pypi@villard.me>
License: Free
Project-URL: Homepage, https://github.com/pypa/sampleproject
Project-URL: Bug Tracker, https://github.com/pypa/sampleproject/issues
Classifier: Programming Language :: Python :: 3
Classifier: License :: OSI Approved :: MIT License
Classifier: Operating System :: OS Independent
Requires-Python: >=3.7
License-File: LICENSE
Requires-Dist: flask
Requires-Dist: flask_cors
Requires-Dist: flask-restful
Requires-Dist: jsonpickle
Requires-Dist: werkzeug
Dynamic: license-file
